qcaas_client/__init__.py
qcaas_client/client.py
qcaas_client/commandline.py
qcaas_client/config.py
scc/compiler/config.py
qcaas_common/__init__.py
qcaas_common/config.py
qcaas_common/enums.py
qcaas_common/json_utils.py
qcaas_common/log_reduct.py
qcaas_common/logger.py
qcaas_common/metrics.py
qcaas_common/type_conversions.py
m4t2wpg7nbxn8agyksx3pcd3mx6-3.0.0.dist-info/LICENSE
m4t2wpg7nbxn8agyksx3pcd3mx6-3.0.0.dist-info/METADATA
m4t2wpg7nbxn8agyksx3pcd3mx6-3.0.0.dist-info/WHEEL
m4t2wpg7nbxn8agyksx3pcd3mx6-3.0.0.dist-info/entry_points.txt
m4t2wpg7nbxn8agyksx3pcd3mx6-3.0.0.dist-info/RECORD
