Metadata-Version: 2.1
Name: m4T2wPG7NBxn8aGyksX3pCD3mX6
Version: 3.0.0
Summary: OQC Quantum Computing as a Service (QCaaS)
License: BSD-3-Clause
Author: OQC
Author-email: oqc_qcaas_support@oxfordquantumcircuits.com
Requires-Python: >=3.9,<3.11
Classifier: License :: OSI Approved :: BSD License
Classifier: Programming Language :: Python :: 3
Classifier: Programming Language :: Python :: 3.9
Classifier: Programming Language :: Python :: 3.10
Provides-Extra: pip-licenses
Requires-Dist: attrs (==21.2.0)
Requires-Dist: bidict (==0.23.1)
Requires-Dist: certifi (==2024.2.2)
Requires-Dist: charset-normalizer (==3.3.2)
Requires-Dist: h11 (==0.14.0)
Requires-Dist: idna (==3.6)
Requires-Dist: markupsafe (==2.1.5)
Requires-Dist: pamqp (==2.3.0)
Requires-Dist: pip-licenses (>=3.5.3,<4.0.0) ; extra == "pip-licenses"
Requires-Dist: python-dotenv (==1.0.1)
Requires-Dist: python-engineio (==4.9.0)
Requires-Dist: python-socketio (==5.5.2)
Requires-Dist: requests (==2.31.0)
Requires-Dist: simple-websocket (==1.0.0)
Requires-Dist: toml (==0.10.2)
Requires-Dist: urllib3 (==2.2.1)
Requires-Dist: wsproto (==1.2.0)
